Metadata-Version: 2.1
Name: ChemistryTool
Version: 0.0.1
Summary: A module that express chemistry phenomenas interms of algoritihms.
Home-page: https://github.com/Besufikad17/ChemistryTool/Python
Author: Besufikad M. Tilahun
Author-email: besumicheal@gmail.com
License: UNKNOWN
Platform: UNKNOWN
Classifier: Programming Language :: Python :: 3
Classifier: License :: OSI Approved :: MIT License
Classifier: Operating System :: OS Independent
Requires-Python: >=3.0
